Metadata-Version: 2.1
Name: check-type-hints
Version: 0.0.4
Summary: Helps you check type hints when you commit code.
Home-page: UNKNOWN
License: UNKNOWN
Platform: UNKNOWN
